researchtikpy/__init__.py
researchtikpy/endpoints.py
researchtikpy/get_access_token.py
researchtikpy/get_followers.py
researchtikpy/get_following.py
researchtikpy/get_liked_videos.py
researchtikpy/get_pinned_videos.py
researchtikpy/get_query.py
researchtikpy/get_users_info.py
researchtikpy/get_video_comments.py
researchtikpy/query_lang.py
researchtikpy/rtk_utilities.py
researchtikpy/shops.py
researchtikpy/social_graph.py
researchtikpy-0.2.2.dist-info/METADATA
researchtikpy-0.2.2.dist-info/WHEEL
researchtikpy-0.2.2.dist-info/licenses/LICENSE
researchtikpy-0.2.2.dist-info/RECORD
