Metadata-Version: 2.4
Name: ResearchTikPy
Version: 0.2.2
Summary: Python API wrapper for the TikTok Research API
Project-URL: Homepage, https://github.com/HohnerJulian/ResearchTikPy
Author-email: Julian Hohner <daswaeldchen@gmail.com>
License-File: LICENSE
Classifier: License :: OSI Approved :: MIT License
Classifier: Operating System :: OS Independent
Classifier: Programming Language :: Python :: 3
Requires-Python: <4.0,>=3.10
Requires-Dist: pandas
Requires-Dist: pydantic
Requires-Dist: requests
Requires-Dist: tqdm
Provides-Extra: dev
Requires-Dist: black; extra == 'dev'
Requires-Dist: isort; extra == 'dev'
Requires-Dist: pytest; extra == 'dev'
